{
  "_links": {
    "self": {
      "href": "/programs/FTEA63001763"
    },
    "parent": {
      "href": "/"
    },
    "next": {
      "href": "/programs/FTEA63001863"
    },
    "share": {
      "href": "https://tv.nrk.no/program/ftea63001763",
      "type": "text/html"
    }
  },
  "seriesId": "fjernsynsteatret",
  "seasonDisplayType": 3,
  "seasonId": "60007",
  "seasonNumber": "1963",
  "episodeNumber": 4,
  "episodeNumberOrDate": "28.02.1963",
  "episodeTitle": "Nedjma",
  "seriesTitle": "Fjernsynsteatret",
  "seriesDescription": "Filmer og teateroppsetninger fra NRKs faste scene.",
  "totalEpisodesInSeason": 19,
  "startNextEpisode": 10,
  "id": "FTEA63001763",
  "title": "Nedjma",
  "originalTitle": "Nedjma",
  "otherTitles": [
    {
      "type": {
        "reference": null,
        "type": "mainTitle"
      },
      "value": "Nedjma"
    },
    {
      "type": {
        "reference": null,
        "type": "originalTitle"
      },
      "value": "Nedjma"
    },
    {
      "type": {
        "reference": null,
        "type": "secondaryTitle"
      },
      "value": "Nedjma"
    },
    {
      "type": {
        "reference": null,
        "type": "secondaryTitle"
      },
      "value": "Nedjma"
    },
    {
      "type": {
        "reference": null,
        "type": "secondaryTitle"
      },
      "value": "Nedjma"
    },
    {
      "type": {
        "reference": null,
        "type": "seriesTitle"
      },
      "value": "Fjernsynsteatret"
    }
  ],
  "sourceMedium": 1,
  "duration": "PT1H48M42.8S",
  "shortDescription": "Krigen i Algerie 1957-62: motstandskampen under unntakstilstanden, og fire unge menn som forelsker seg i samme kvinne. NB: Flimmer på båndet de første 2 minuttene.",
  "longDescription": "Av den algirske dramatikeren Kateb Yacine.\nOversatt av Gidske Anderson og Helge Hagerup.\nInnledning ved Yngvar Ustvedt.\nMusikk: Gilbert Amy.\nDekor og kostymer: Guy Krohg.\nSkuespill om krigen i Algerie 1957-62.  Motstandskamp under unntaksstillstanden\nsom var innført av de franske troppene.  Gjenomgangsfiguren Lakhdars\nopplevelser.\nFilminnslag rull 1:\nEO: Unge algirske studenter uttaler seg om situasjonen i Algerie.  Stillbilder\nto småpiker, liten gutt spiser brød, to tilslørede kvinner snakker sammen,\nfolkevrimmel, nært forskjellige typer, gutt med store bedende øyne. 5'41\".\nFilminnslag rull 2:\nFolkevrimmel i Alger-gate.  Avisgutt roper.  Folk i busskø.  Pakke leveres fra\nden ene til den andre.  Flere shots folk.  Buss kjører fra holdeplass. 1'33\".\nBuss i gate. 0'14\".  KJøring langs Alger havn i buss. 0'14\".\nTrafikkscener i Alger. 0'09\". Scener fra buss gjennom gater. 0'24\".\nBuss forbi små boder. 0'06\".  Buss forbi kamera.  0'06\".\nBuss sviner opp til holdeplass. 0'14\".\nNært guttunge.  Folk ut av buss.  Gutten løper og får pakke, løper gjennom\ngater med den. 0'30\".  Til hit: EO.\nAU: OAS-opptøyer i Algerie, 0'36\".\nEO: Gutt løper opp trapper med pakke. 0'06\".\nAU: Flybilder folkehav, de GAULLE i Alger, OAS-opptøyer. 0'36\".\nEO: Gutten løper opp trapper. 0'05\".\nAU: Folkehav, soldater, tanks. 0'42\".\nEO: Gutten løper videre. 0'07\".\nAU: Pro-FLN demonstrasjon.  Evianforhandlinger. 0'42\".\nEO: Gutten løper videre. 0'08\".\nAU: OAS-opptøyer. 0'34\".\nEO: Gutten igjen.  Folkemengde.  Utsyn over bygninger og flagg i Alger. 0'38\".\nFilminnslag rull 3:\nEO:  Nært forskj. typer.  Torghandel og folkemengde.  Skilt \"Rue des Vandales\".\nFlere scener fra gaten med vrimmel av småbarn, voksne og gamle.  Klokkeselger.\nNært typer.  Skyer.  Flere shots ruiner.  Landsby i fjellene.  Sverd i\nfjellsprekk.  Kjøring over gresslette.  Stor gribb i luften (AU?)  3'18\".\nEO:  Nært folkevrimmel.  Scener fra tov.  Gate med små barn, nærb.  Nært\nforskj. typer.  Skyer.  Ruiner.  Festning.  Sverd i fjellsprekk. 2'57\".\nEO: Kjøring med kamera over gravplasser med moske i bakgrunnen.  Kjøring i full\nfart over gresslette.  Ruiner.  Gribb i luften (AU?). 1'18\".\nEO: Nært folk.  Fiskesalg.  Bydel i Alger.  Gutt gir mynt til gammel mann.\nNært forskj. typer.  Skyer.  Ruiner.  Gravstener.  Stener velter.  Gribb i\nluften (AU?).  Tre i fjellsprekk.  2'27\".\nFilminnslag rull 4:\nEO:  Folkevrimmel, tre kutt. 0'16\", 0'18\" og 0'18\".  Nærmere bilde\nfolkevrimmel.  Flagg festes på tak. 0'26\".  Gribb i luften (AU?).  0'16\".\nNært sovende gutt.  Gutten våkner og løper avsted i gater. 0'26\".\nFilminnslag rull 5:\nEO:  Scener fra busstur i Alger. 1'56\".\nI rollene:\nLakhdar .................. Espen SKJØNBERG\nNedjma ................... Monna TANDBERG\nHassan ................... Sverre HANSEN\nMustapha ................. Joachim CALMEYER\nTahar .................... Per GJERSØE\nMarguerite ............... Brett BORGEN\nGateselgeren ............. Jens BOLLING\nPolitisjefen ............. Thor HJORTH-JENSSEN\nCaiden ................... Toralf SANDØ\nZohra .................... Ella HVAL\nMustaphas mor ............ Mona HOFLAND\nBudbringeren ............. Johan HOLST\nMajoren .................. Henrik Anker STEEN\nOffiserer ................ Magne BLENESS\n                           Roy BJØRNSTAD\nEn fellah ................ Frimann Falck CLAUSEN",
  "image": {
    "imageInfo": {
      "id": "B4GSUBSuMbDtyXvqQ-5vfA",
      "cropInfo": {
        "x": 0.0,
        "y": 0.0489563569,
        "width": 1.0,
        "height": 0.7343454
      }
    },
    "imageWidthCropInfo": "B4GSUBSuMbDtyXvqQ-5vfA?x=0.00000000000000000&y=0.04895635673624289&w=1.00000000000000000&h=0.73434535104364330",
    "webImages": [
      {
        "imageUrl": "https://gfx.nrk.no/B4GSUBSuMbDtyXvqQ-5vfAawyCn7XcHLrQERM8PoGATA",
        "pixelWidth": 300
      },
      {
        "imageUrl": "https://gfx.nrk.no/B4GSUBSuMbDtyXvqQ-5vfASKyRjzSLI8zQERM8PoGATA",
        "pixelWidth": 600
      },
      {
        "imageUrl": "https://gfx.nrk.no/B4GSUBSuMbDtyXvqQ-5vfAVqwpk4KgeiHQERM8PoGATA",
        "pixelWidth": 960
      },
      {
        "imageUrl": "https://gfx.nrk.no/B4GSUBSuMbDtyXvqQ-5vfApEVMvgMtZGvQERM8PoGATA",
        "pixelWidth": 1920
      }
    ],
    "isDefaultImage": false
  },
  "subjectList": [],
  "mentionedList": [],
  "programAndIndexPointsSubjectList": [],
  "programAndIndexPointsContributors": [
    {
      "name": "Thor Hjorth-Jenssen",
      "role": "Skuespiller",
      "givenName": "Thor",
      "familyName": "Hjorth-Jenssen"
    },
    {
      "name": "Mona Hofland",
      "role": "Skuespiller",
      "givenName": "Mona",
      "familyName": "Hofland"
    },
    {
      "name": "Frimann Falck Clausen",
      "role": "Skuespiller",
      "givenName": "Frimann Falck",
      "familyName": "Clausen"
    },
    {
      "name": "Johan Holst",
      "role": "Skuespiller",
      "givenName": "Johan",
      "familyName": "Holst"
    },
    {
      "name": "Brett Borgen",
      "role": "Skuespiller",
      "givenName": "Brett",
      "familyName": "Borgen"
    },
    {
      "name": "Espen Skjønberg",
      "role": "Skuespiller",
      "givenName": "Espen",
      "familyName": "Skjønberg"
    },
    {
      "name": "Monna Tandberg",
      "role": "Skuespiller",
      "givenName": "Monna",
      "familyName": "Tandberg"
    },
    {
      "name": "Sverre Hansen",
      "role": "Skuespiller",
      "givenName": "Sverre",
      "familyName": "Hansen"
    },
    {
      "name": "Joachim Calmeyer",
      "role": "Skuespiller",
      "givenName": "Joachim",
      "familyName": "Calmeyer"
    },
    {
      "name": "Per Gjersøe",
      "role": "Skuespiller",
      "givenName": "Per",
      "familyName": "Gjersøe"
    },
    {
      "name": "Jens Bolling",
      "role": "Skuespiller",
      "givenName": "Jens",
      "familyName": "Bolling"
    },
    {
      "name": "Toralf Sandø",
      "role": "Skuespiller",
      "givenName": "Toralf",
      "familyName": "Sandø"
    },
    {
      "name": "Ella Hval",
      "role": "Skuespiller",
      "givenName": "Ella",
      "familyName": "Hval"
    },
    {
      "name": "Henrik Anker Steen",
      "role": "Skuespiller",
      "givenName": "Henrik Anker",
      "familyName": "Steen"
    },
    {
      "name": "Magne Bleness",
      "role": "Skuespiller",
      "givenName": "Magne",
      "familyName": "Bleness"
    },
    {
      "name": "Roy Bjørnstad",
      "role": "Skuespiller",
      "givenName": "Roy",
      "familyName": "Bjørnstad"
    }
  ],
  "programAndIndexPointsMentionedList": [],
  "firstTimeTransmitted": {
    "publicationDate": "/Date(-215917200000+0100)/",
    "actualTransmissionDate": "/Date(-215917200000+0100)/",
    "channelId": "nrk1",
    "channelName": "NRK1",
    "isRerun": false
  },
  "nextPlannedTransmissions": [],
  "lastTimeTransmitted": {
    "publicationDate": "/Date(-215917200000+0100)/",
    "actualTransmissionDate": "/Date(-215917200000+0100)/",
    "channelId": "nrk1",
    "channelName": "NRK1",
    "isRerun": false
  },
  "legalAge": {
    "id": "12",
    "displayValue": "Aldersgrense 12 år",
    "displayAge": "12+"
  },
  "category": {
    "id": "kultur",
    "displayValue": "Kultur",
    "isTvCategory": true,
    "isRadioCategory": true
  },
  "externalLinks": [],
  "usageRights": {
    "isGeoBlocked": false,
    "availableFrom": "/Date(1396670100000+0200)/",
    "availableTo": "/Date(4102437600000+0100)/",
    "hasRightsNow": true
  },
  "availability": {
    "status": "available",
    "hasLabel": false,
    "label": null
  },
  "indexPoints": null,
  "categories": [
    {
      "id": "kultur",
      "displayValue": "Kultur",
      "isTvCategory": true,
      "isRadioCategory": true
    },
    {
      "id": "nrk-arkivet",
      "displayValue": "NRK-arkivet",
      "isTvCategory": true,
      "isRadioCategory": false
    },
    {
      "id": "drama-serier",
      "displayValue": "Drama/serier",
      "isTvCategory": true,
      "isRadioCategory": false
    }
  ],
  "contributors": [
    {
      "name": "Thor Hjorth-Jenssen",
      "role": "Skuespiller",
      "givenName": "Thor",
      "familyName": "Hjorth-Jenssen"
    },
    {
      "name": "Mona Hofland",
      "role": "Skuespiller",
      "givenName": "Mona",
      "familyName": "Hofland"
    },
    {
      "name": "Frimann Falck Clausen",
      "role": "Skuespiller",
      "givenName": "Frimann Falck",
      "familyName": "Clausen"
    },
    {
      "name": "Johan Holst",
      "role": "Skuespiller",
      "givenName": "Johan",
      "familyName": "Holst"
    },
    {
      "name": "Brett Borgen",
      "role": "Skuespiller",
      "givenName": "Brett",
      "familyName": "Borgen"
    },
    {
      "name": "Espen Skjønberg",
      "role": "Skuespiller",
      "givenName": "Espen",
      "familyName": "Skjønberg"
    },
    {
      "name": "Monna Tandberg",
      "role": "Skuespiller",
      "givenName": "Monna",
      "familyName": "Tandberg"
    },
    {
      "name": "Sverre Hansen",
      "role": "Skuespiller",
      "givenName": "Sverre",
      "familyName": "Hansen"
    },
    {
      "name": "Joachim Calmeyer",
      "role": "Skuespiller",
      "givenName": "Joachim",
      "familyName": "Calmeyer"
    },
    {
      "name": "Per Gjersøe",
      "role": "Skuespiller",
      "givenName": "Per",
      "familyName": "Gjersøe"
    },
    {
      "name": "Jens Bolling",
      "role": "Skuespiller",
      "givenName": "Jens",
      "familyName": "Bolling"
    },
    {
      "name": "Toralf Sandø",
      "role": "Skuespiller",
      "givenName": "Toralf",
      "familyName": "Sandø"
    },
    {
      "name": "Ella Hval",
      "role": "Skuespiller",
      "givenName": "Ella",
      "familyName": "Hval"
    },
    {
      "name": "Henrik Anker Steen",
      "role": "Skuespiller",
      "givenName": "Henrik Anker",
      "familyName": "Steen"
    },
    {
      "name": "Magne Bleness",
      "role": "Skuespiller",
      "givenName": "Magne",
      "familyName": "Bleness"
    },
    {
      "name": "Roy Bjørnstad",
      "role": "Skuespiller",
      "givenName": "Roy",
      "familyName": "Bjørnstad"
    }
  ],
  "mediaAssetsOnDemand": [
    {
      "part": 1,
      "urlPattern": "https://psapi.nrk.no/obsoleteproperty?endpoint=programs/FTEA63001763&property=UrlPattern&useragent=python-requests%2f2.32.5",
      "duration": "PT1H48M43S",
      "bitrates": [
        0
      ],
      "webVttSubtitles": "https://psapi.nrk.no/obsoleteproperty?endpoint=programs/FTEA63001763&property=WebVttSubtitles&useragent=python-requests%2f2.32.5",
      "timedTextSubtitlesUrl": "https://psapi.nrk.no/obsoleteproperty?endpoint=programs/FTEA63001763&property=TimedTextSubtitlesUrl&useragent=python-requests%2f2.32.5",
      "hdsUrl": "https://psapi.nrk.no/obsoleteproperty?endpoint=programs/FTEA63001763&property=HdsUrl&useragent=python-requests%2f2.32.5",
      "hlsUrl": "https://psapi.nrk.no/obsoleteproperty?endpoint=programs/FTEA63001763&property=HlsUrl&useragent=python-requests%2f2.32.5",
      "carrierId": "FTEA000063-AR-199415980"
    }
  ],
  "relatedProgramsBox": 1,
  "hasReview": false,
  "programUrlMetadata": "28-02-1963",
  "isInLiveBuffer": false,
  "liveBufferTransmissionChannel": null,
  "liveBufferTransmissionStartTime": null,
  "showLiveBuffer": false,
  "hasSubtitles": false,
  "subtitlesDefaultOn": false,
  "carrierId": "FTEA000063-AR-199415980",
  "isInSuperUniverse": false,
  "reviewUrl": null,
  "promoLabels": [],
  "productionYear": 1963
}